README
setup.py
sakura/__init__.py
sakura/buffer_reader.py
sakura/buffer_writer.py
sakura/cache.py
sakura/config.py
sakura/conhash.py
sakura/convert.py
sakura/crypt.py
sakura/daemon.py
sakura/event_loop.py
sakura/gtcpasyncclient.py
sakura/gtcpclient.py
sakura/ipc.py
sakura/jsonutils.py
sakura/logger.py
sakura/loggerconfig.py
sakura/loggingmp.py
sakura/oamutils.py
sakura/osutils.py
sakura/pbutils.py
sakura/simplequeue.py
sakura/tcp_server.py
sakura/utils.py
sakura/version_tools.py
sakura.egg-info/PKG-INFO
sakura.egg-info/SOURCES.txt
sakura.egg-info/dependency_links.txt
sakura.egg-info/requires.txt
sakura.egg-info/top_level.txt