Metadata-Version: 1.1
Name: sakura
Version: 0.1.7
Summary: sakura
Home-page: https://github.com/nevermoreluo/sakura
Author: sakura
Author-email: sakura@nonono.rocks
License: UNKNOWN
Download-URL: https://github.com/nevermoreluo/sakura/archive/master.zip
Platform: UNKNOWN
